[
  {
    "section_title": "تعريفات",
    "content": [
      {
        "title": "عابر الطريق",
        "description": "كل من يستعمل الطريق للسفر أو المشي أو الوقوف."
      },
      {
        "title": "مركبة آلیة",
        "description": "كل مركبة تسير بقوة ميكانيكية مهما كان نوعها."
      },
      {
        "title": "المركبة",
        "description": "المركبة التي تسير بقوة آلية أو تجر بواسطة مركبة أو حيوان."
      },
      {
        "title": "الطريق",
        "description": "كل مكان مفتوح يحق للجمهور المرور فيه وتشمل كل شارع، نفق، جسر، إلخ."
      },
      {
        "title": "الشارع",
        "description": "قسم من الطريق معد لسير المركبات فقط."
      },
      {
        "title": "المساحة الفاصلة",
        "description": "كل مكان غير مخصص لسير المركبات ويقع بين قسمين من الطريق."
      },
      {
        "title": "خط التوقف",
        "description": "خط مرسوم على عرض الطريق أو على قسم منها الذي يُشكل حداً لوقوف مركبة."
      },
      {
        "title": "السبيل",
        "description": "طريق أو قسم من الطريق خصص لنوع معين من عابري الطريق."
      },
      {
        "title": "طرف الطريق",
        "description": "المساحة المجاورة لحافة طريق المركبات الخالية من الرصيف."
      },
      {
        "title": "الرصیف",
        "description": "قسم من عرض الطريق غير معد لسير المركبات ويقع بجانب طريق المركبات وخصص للمارة."
      },
      {
        "title": "طريق ذات اتجاه واحد",
        "description": "طريق مسموح فيها بحركة السير في اتجاه واحد."
      },
      {
        "title": "طريق ذات اتجاهين",
        "description": "طريق يجوز فيها السير في الاتجاهين."
      },
      {
        "title": "الطريق المغلقة من الجهتين",
        "description": "تعتبر طريق في نظر القانون."
      },
      {
        "title": "الاستدارة",
        "description": "تغيير المسلك وتغيير اتجاه المركبة."
      },
      {
        "title": "الطريق السريعة",
        "description": "كل طريق خارج المدن ذو اتجاهين أو أكثر تفصل بينهما منطقة فاصلة وخصص لحركة المركبات الآلية فقط."
      },
      {
        "title": "الليل ووقت الإنارة",
        "description": "الليل هو الفترة التي تبدأ بعد ربع ساعة من غروب الشمس وتنتهي قبل ربع ساعة من شروقها."
      },
      {
        "title": "الحیوانات",
        "description": "الدواب والحيوانات الأليفة باستثناء الكلاب والقطط والطيوور الداجنة."
      },
      {
        "title": "ماكنة متنقلة",
        "description": "مركبة ميكانيكية معدة لتنفيذ أعمال ولكنها ليست معدة للجر."
      },
      {
        "title": "المركبة الخصوصية",
        "description": "المركبة المعدة للاستعمال الشخصي."
      },
      {
        "title": "المركبة التجارية",
        "description": "المركبة المعدة للاستعمال في نقل البضائع لقاء أجرة أو ما يتعلق بنقلها في أعمال صاحب المركبة أو تجارته."
      },
      {
        "title": "حق الأولوية",
        "description": "عدم مواصلة قائد المركبة السير أو عدم البدء فيه إذا كان استمرار سيره سيعرض الآخرين للخطر."
      },
      {
        "title": "الوقوف",
        "description": "وجود المركبة في مكان ما لفترة محددة أو غير محددة وليس لغرض نقل الركاب أو إنزالهم."
      },
      {
        "title": "مركبة أمن",
        "description": "مركبة الإسعاف، الشرطة، أو الإطفاء والمركبات المخصصة لحفظ الأمن."
      },
      {
        "title": "طريق بلدية",
        "description": "كل طريق يقع ضمن اختصاصات سلطة محلية."
      },
      {
        "title": "الدراجة النارية",
        "description": "مركبة ميكانيكية لها عجلتين مركبتان واحدة خلف الأخرى."
      },
      {
        "title": "مركبة عمل",
        "description": "المركبة التي ركبت فيها أجهزة عمل ثابتة أو المعدة لتنفيذ عمل."
      }
    ]
  },
  {
    
  }
]
